src/game/__init__.py
src/game/definitions.py
src/game/main.py
src/game/settings.py
src/game/utils.py
src/game/walk_the_loop.py
src/game/pieces/__init__.py
src/game/pieces/edge.py
src/game/pieces/icons.py
src/game/pieces/node.py
src/game/pieces/path.py
src/game/pieces/player.py
src/game/pieces/players.py
venv/bin/activate_this.py
venv/lib/python3.10/site-packages/_virtualenv.py
venv/lib/python3.10/site-packages/_distutils_hack/__init__.py
venv/lib/python3.10/site-packages/_distutils_hack/override.py
venv/lib/python3.10/site-packages/more_itertools/__init__.py
venv/lib/python3.10/site-packages/more_itertools/more.py
venv/lib/python3.10/site-packages/more_itertools/recipes.py
venv/lib/python3.10/site-packages/pip/__init__.py
venv/lib/python3.10/site-packages/pip/__main__.py
venv/lib/python3.10/site-packages/pip/__pip-runner__.py
venv/lib/python3.10/site-packages/pip/_internal/__init__.py
venv/lib/python3.10/site-packages/pip/_internal/build_env.py
venv/lib/python3.10/site-packages/pip/_internal/cache.py
venv/lib/python3.10/site-packages/pip/_internal/configuration.py
venv/lib/python3.10/site-packages/pip/_internal/exceptions.py
venv/lib/python3.10/site-packages/pip/_internal/main.py
venv/lib/python3.10/site-packages/pip/_internal/pyproject.py
venv/lib/python3.10/site-packages/pip/_internal/self_outdated_check.py
venv/lib/python3.10/site-packages/pip/_internal/wheel_builder.py
venv/lib/python3.10/site-packages/pip/_internal/cli/__init__.py
venv/lib/python3.10/site-packages/pip/_internal/cli/autocompletion.py
venv/lib/python3.10/site-packages/pip/_internal/cli/base_command.py
venv/lib/python3.10/site-packages/pip/_internal/cli/cmdoptions.py
venv/lib/python3.10/site-packages/pip/_internal/cli/command_context.py
venv/lib/python3.10/site-packages/pip/_internal/cli/main.py
venv/lib/python3.10/site-packages/pip/_internal/cli/main_parser.py
venv/lib/python3.10/site-packages/pip/_internal/cli/parser.py
venv/lib/python3.10/site-packages/pip/_internal/cli/progress_bars.py
walk_the_loop-0.0.2.dist-info/METADATA
walk_the_loop-0.0.2.dist-info/WHEEL
walk_the_loop-0.0.2.dist-info/licenses/LICENSE
walk_the_loop-0.0.2.dist-info/RECORD
