Metadata-Version: 2.1
Name: Walk_The_Loop
Version: 0.0.2
Summary: A simple game to learn about hamiltonian cycles, by doing
Project-URL: Homepage, https://github.com/discocube/walk_the_loop
Project-URL: Bug Tracker, https://github.com/discocube/walk_the_loop/issues
Author-email: Rommelo Yu <rommelo@rommelo.com>
License-File: LICENSE
Classifier: License :: OSI Approved :: GNU Affero General Public License v3 or later (AGPLv3+)
Classifier: Operating System :: OS Independent
Classifier: Programming Language :: Python :: 3
Requires-Python: >=3.10
